avarana/__init__.py
avarana/ts_forecast.py
avarana-0.5.3.dist-info/METADATA
avarana-0.5.3.dist-info/WHEEL
avarana-0.5.3.dist-info/top_level.txt
avarana-0.5.3.dist-info/RECORD
