Metadata-Version: 2.1
Name: avarana
Version: 0.5.3
Summary: Wrappers and functions for predictive modeling
Home-page: https://github.com/hrajiv
Author: Rajiv HS
Author-email: rajivhs@gmail.com
License: MIT
Platform: UNKNOWN
